pornstar/_CV2_filters.py
pornstar/_PIL_filters.py
pornstar/__init__.py
pornstar/_audio_module.py
pornstar/_main.py
pornstar/_my_deeplab.py
pornstar/_my_dlib.py
pornstar/_my_object_detector.py
pornstar/_nsfw_detector.py
pornstar/_white_model.py
pornstar/effects.py
pornstar/face.py
pornstar/store.py
pornstar/utils.py
pornstar/static/mask.png
pornstar/static/mscoco_label_map.pbtxt
pornstar-0.7.dist-info/METADATA
pornstar-0.7.dist-info/WHEEL
pornstar-0.7.dist-info/top_level.txt
pornstar-0.7.dist-info/RECORD
