Metadata-Version: 2.1
Name: pornstar
Version: 0.7
Summary: Make you become the next porn star!
Home-page: https://github.com/yingshaoxo/pornstar
Author: yingshaoxo
Author-email: yingshaoxo@gmail.com
License: MIT
Keywords: pornstar
Platform: UNKNOWN
Classifier: Operating System :: POSIX :: Linux
Classifier: Programming Language :: Python :: 3
Classifier: Topic :: System
Classifier: License :: OSI Approved :: MIT License
Requires-Dist: setuptools
Requires-Dist: auto-everything
Requires-Dist: numpy
Requires-Dist: matplotlib
Requires-Dist: pillow
Requires-Dist: moviepy
Requires-Dist: dlib
Requires-Dist: opencv-python
